MANIFEST.in
setup.cfg
setup.py
chunksub/__init__.py
chunksub/chunksub.py
chunksub/default_config.yml
chunksub.egg-info/PKG-INFO
chunksub.egg-info/SOURCES.txt
chunksub.egg-info/dependency_links.txt
chunksub.egg-info/entry_points.txt
chunksub.egg-info/requires.txt
chunksub.egg-info/top_level.txt
chunksub/job_templates/default.template