Metadata-Version: 1.0
Name: chunksub
Version: 0.1.3
Summary: Submit jobs in chunks on a qsub-based cluster. *Like `parallel` only for qsub*
Home-page: https://github.com/grst/chunksub
Author: Gregor Sturm
Author-email: gregor.sturm@cs.tum.edu
License: GPLv3
Keywords: bioinformatics,sge,torque,hpc,slurm,parallel
Platform: UNKNOWN
